[
  {
    "id": 1,
    "name": "Jacket",
    "price": 31
  },
  {
    "id": 2,
    "name": "Coat",
    "price": 74
  },
  {
    "id": 3,
    "name": "Trousers",
    "price": 45
  },
  {
    "id": 4,
    "name": "Shorts",
    "price": 39
  },
  {
    "id": 5,
    "name": "Underwear",
    "price": 29
  },
  {
    "id": 6,
    "name": "Suit",
    "price": 34
  },
  {
    "id": 7,
    "name": "Skirt",
    "price": 45
  },
  {
    "id": 8,
    "name": "Dress",
    "price": 76
  },
  {
    "id": 9,
    "name": "Shoes",
    "price": 33
  },
  {
    "id": 10,
    "name": "Boots",
    "price": 72
  },
  {
    "id": 11,
    "name": "Slippers",
    "price": 42
  },
  {
    "id": 12,
    "name": "Sweater",
    "price": 64
  },
  {
    "id": 13,
    "name": "Waistcoat",
    "price": 95
  }
]